dupin/__init__.py
dupin/errors.py
dupin/postprocessing.py
dupin/data/__init__.py
dupin/data/aggregate.py
dupin/data/base.py
dupin/data/freud.py
dupin/data/logging.py
dupin/data/map.py
dupin/data/reduce.py
dupin/data/spatial.py
dupin/detect/__init__.py
dupin/detect/costs.py
dupin/detect/detect.py
dupin/preprocessing/__init__.py
dupin/preprocessing/filter.py
dupin/preprocessing/signal.py
dupin/preprocessing/supervised.py
dupin-0.2.dist-info/AUTHORS.rst
dupin-0.2.dist-info/LICENSE
dupin-0.2.dist-info/METADATA
dupin-0.2.dist-info/WHEEL
dupin-0.2.dist-info/top_level.txt
dupin-0.2.dist-info/RECORD
