Metadata-Version: 2.2
Name: dupin
Version: 0.2
Summary: Offline and online event detection scheme for rare events in molecular simulations.
Author-email: "Brandon Butler et al." <butlerbr@umich.edu>
Maintainer-email: Brandon Butler <butlerbr@umich.edu>
Project-URL: Source, https://github.com/glotzerlab/dupin
Project-URL: Documentation, https://dupin.readthedocs.io
Project-URL: Issues, https://github.com/glotzerlab/dupin/issues
Keywords: event detection,molecular simulations
Classifier: Development Status :: 4 - Beta
Classifier: Natural Language :: English
Classifier: Programming Language :: Python :: 3
Classifier: Programming Language :: Python :: 3.9
Classifier: Programming Language :: Python :: 3.10
Classifier: Programming Language :: Python :: 3.11
Classifier: Programming Language :: Python :: 3.12
Classifier: Programming Language :: Python :: 3.13
Requires-Python: >=3.9
License-File: LICENSE
License-File: AUTHORS.rst
